gpa_api/__init__.py
gpa_api/__main__.py
gpa_api/encoder.py
gpa_api/typing_utils.py
gpa_api/util.py
gpa_api/controllers/__init__.py
gpa_api/controllers/lng_controller.py
gpa_api/controllers/security_controller_.py
gpa_api/models/__init__.py
gpa_api/models/base_model_.py
gpa_api/models/calculation.py
gpa_api/models/calculation_body.py
gpa_api/models/calculation_step.py
gpa_api/models/fluid.py
gpa_api/models/metric.py
gpa_api/models/ship.py
gpa_api/models/standard.py
gpa_api/models/transport.py
gpa_api/openapi/openapi.yaml
gpa_api/test/__init__.py
gpa_api/test/test_lng_controller.py
gpa_api-0.0.1.dist-info/METADATA
gpa_api-0.0.1.dist-info/WHEEL
gpa_api-0.0.1.dist-info/entry_points.txt
gpa_api-0.0.1.dist-info/top_level.txt
gpa_api-0.0.1.dist-info/RECORD
