Metadata-Version: 2.1
Name: gpa-api
Version: 0.0.1
Summary: GPA API
Home-page: UNKNOWN
Author: UNKNOWN
Author-email: UNKNOWN
License: UNKNOWN
Keywords: OpenAPI,GPA API
Platform: UNKNOWN
Requires-Dist: connexion (>=2.0.2)
Requires-Dist: swagger-ui-bundle (>=0.0.2)
Requires-Dist: python-dateutil (>=2.6.0)
